pytest_local_badge/__init__.py
pytest_local_badge/badges.py
pytest_local_badge/plugin.py
pytest_local_badge/svg_badge.py
pytest_local_badge-1.0.3.dist-info/LICENSE
pytest_local_badge-1.0.3.dist-info/METADATA
pytest_local_badge-1.0.3.dist-info/WHEEL
pytest_local_badge-1.0.3.dist-info/entry_points.txt
pytest_local_badge-1.0.3.dist-info/top_level.txt
pytest_local_badge-1.0.3.dist-info/RECORD
