Metadata-Version: 2.1
Name: pytest-local-badge
Version: 1.0.3
Summary: Generate local badges (shields) reporting your test suite status.
Home-page: https://github.com/VRGhost/pytest-local-badge
Author: Ilja Orlovs
Author-email: vrghost@gmail.com
License: MIT
Classifier: Environment :: Plugins
Classifier: Framework :: Pytest
Classifier: License :: OSI Approved :: MIT License
Classifier: Programming Language :: Python :: 3.7
Classifier: Programming Language :: Python :: 3.8
Classifier: Programming Language :: Python :: 3.9
Classifier: Programming Language :: Python :: 3.10
Requires-Python: >=3.7
License-File: LICENSE
Requires-Dist: pytest (>=6.1.0)
Provides-Extra: develop
Requires-Dist: black (>=22.12.0) ; extra == 'develop'
Requires-Dist: pytest (<8,>=7.1.0) ; extra == 'develop'
Requires-Dist: pytest-cov ; extra == 'develop'
Requires-Dist: pytest-mock ; extra == 'develop'
Requires-Dist: flake8-bugbear ; extra == 'develop'
Requires-Dist: flake8-import-order ; extra == 'develop'
Requires-Dist: pep8-naming ; extra == 'develop'
Requires-Dist: flake8-print ; extra == 'develop'
Requires-Dist: flake8-comprehensions ; extra == 'develop'
Requires-Dist: build ; extra == 'develop'
